{
    "ids": [
        {"id": "AAAAA"},
        {"id": "BBBBB"},
        {"id": "CCCCC"},
        {"id": "DDDDD"},
        {"id": "EEEEE"},
        {"id": "FFFFF"},
        {"id": "GGGGG"},
        {"id": "HHHHH"},
        {"id": "IIIII"},
        {"id": "JJJJJ"},
        {"id": "KKKKK"},
        {"id": "LLLLL"},
        {"id": "MMMMM"},
        {"id": "NNNNN"},
        {"id": "OOOOO"},
        {"id": "PPPPP"},
        {"id": "QQQQQ"},
        {"id": "RRRRR"}
    ],
    "links": [
        {"from": "AAAAA", "to": "BBBBB"},
        {"from": "BBBBB", "to": "CCCCC"},
        {"from": "AAAAA", "to": "CCCCC"},
        {"from": "AAAAA", "to": "DDDDD"},
        {"from": "DDDDD", "to": "FFFFF"},
        {"from": "FFFFF", "to": "GGGGG"},
        {"from": "AAAAA", "to": "HHHHH"},
        {"from": "GGGGG", "to": "JJJJJ"},
        {"from": "GGGGG", "to": "HHHHH"},
        {"from": "JJJJJ", "to": "KKKKK"},
        {"from": "KKKKK", "to": "LLLLL"},
        {"from": "BBBBB", "to": "LLLLL"},
        {"from": "LLLLL", "to": "MMMMM"},
        {"from": "EEEEE", "to": "NNNNN"},
        {"from": "HHHHH", "to": "MMMMM"},
        {"from": "MMMMM", "to": "IIIII"},
        {"from": "MMMMM", "to": "EEEEE"},
        {"from": "AAAAA", "to": "OOOOO"},
        {"from": "AAAAA", "to": "PPPPP"},
        {"from": "AAAAA", "to": "QQQQQ"},
        {"from": "AAAAA", "to": "RRRRR"},
        {"from": "OOOOO", "to": "HHHHH"},
        {"from": "QQQQQ", "to": "EEEEE"},
        {"from": "PPPPP", "to": "IIIII"}
    ]
}